grafana_metrics/__init__.py
grafana_metrics/config.py
grafana_metrics/main.py
grafana_metrics/thread_utils.py
grafana_metrics/utils.py
grafana_metrics/engines/__init__.py
grafana_metrics/engines/base.py
grafana_metrics/engines/influx.py
grafana_metrics/metrics/__init__.py
grafana_metrics/metrics/base.py
grafana_metrics/metrics/cpu.py
grafana_metrics/metrics/disk.py
grafana_metrics/metrics/memory.py
grafana_metrics/metrics/nginx.py
grafana_metrics/metrics/postgresql_metric.py
grafana_metrics/metrics/redis_metric.py
grafana_metrics/metrics/selectel_cdn.py
grafana_metrics-1.1.3.dist-info/LICENSE
grafana_metrics-1.1.3.dist-info/METADATA
grafana_metrics-1.1.3.dist-info/WHEEL
grafana_metrics-1.1.3.dist-info/entry_points.txt
grafana_metrics-1.1.3.dist-info/top_level.txt
grafana_metrics-1.1.3.dist-info/RECORD
